momiji/__init__.py
momiji/models/__init__.py
momiji/models/model.py
momiji/predict/__init__.py
momiji/predict/predict.py
momiji/preprocess/__init__.py
momiji/preprocess/_preprocess.py
momiji/preprocess/_preprocess_utils.py
momiji/run.py
momiji-0.1.3.dist-info/LICENSE
momiji-0.1.3.dist-info/METADATA
momiji-0.1.3.dist-info/WHEEL
momiji-0.1.3.dist-info/RECORD
