Metadata-Version: 2.1
Name: momiji
Version: 0.1.3
Summary: For verification of library development
License: BSD-2-Clause
Author: openaging
Author-email: open.aging.info@gmail.com
Requires-Python: >=3.10,<4.0
Classifier: License :: OSI Approved :: BSD License
Classifier: Programming Language :: Python :: 3
Classifier: Programming Language :: Python :: 3.10
Classifier: Programming Language :: Python :: 3.11
Classifier: Programming Language :: Python :: 3.12
Requires-Dist: anndata (>=0.10.3,<0.11.0)
Requires-Dist: numpy (>=1.26.2,<2.0.0)
Requires-Dist: pandas (>=2.1.3,<3.0.0)
Requires-Dist: scikit-learn (>=1.3.2,<2.0.0)
Requires-Dist: torch (>=2.1.1,<3.0.0)
